codeanalyst/__init__.py
codeanalyst/codeanalyst.py
codeanalyst/data.py
codeanalyst-0.7.dist-info/METADATA
codeanalyst-0.7.dist-info/WHEEL
codeanalyst-0.7.dist-info/top_level.txt
codeanalyst-0.7.dist-info/RECORD
