Metadata-Version: 2.1
Name: codeanalyst
Version: 0.7
Summary: Nothing
Home-page: https://notavailable.live
Author: ProgrammingError
Author-email: error@notavailable.live
License: UNKNOWN
Platform: UNKNOWN
Classifier: Programming Language :: Python :: 3
Classifier: License :: OSI Approved :: MIT License
Classifier: Operating System :: OS Independent
Requires-Python: >=3.6
